[
    {
        "word": "social",
        "meaning": "사회의",
        "bolded": "**social**"
    },
    {
        "word": "moral",
        "meaning": "도덕적인; 교훈, (pl.) 도덕",
        "bolded": "**moral**"
    },
    {
        "word": "ethic",
        "meaning": "윤리, 도덕",
        "bolded": "**ethic**"
    },
    {
        "word": "tend",
        "meaning": "~하는 경향이 있다, ~하기 쉽다",
        "bolded": "**tend**"
    },
    {
        "word": "allow",
        "meaning": "허락하다, 허가하다",
        "bolded": "**allow**"
    },
    {
        "word": "affect",
        "meaning": "~에 영향을 미치다",
        "bolded": "**affect**"
    },
    {
        "word": "expire",
        "meaning": "만기가 되다",
        "bolded": "**expire**"
    },
    {
        "word": "organization",
        "meaning": "조직, 단체, 기구",
        "bolded": "**organization**"
    },
    {
        "word": "liberty",
        "meaning": "자유; 해방, 석방",
        "bolded": "**liberty**"
    },
    {
        "word": "factor",
        "meaning": "요소, 요인",
        "bolded": "**factor**"
    },
    {
        "word": "opportunity",
        "meaning": "기회",
        "bolded": "**opportunity**"
    },
    {
        "word": "standard",
        "meaning": "표준, 기준; 표준의",
        "bolded": "**standard**"
    },
    {
        "word": "status",
        "meaning": "지위, 신분; 상태",
        "bolded": "**status**"
    },
    {
        "word": "facility",
        "meaning": "편의, 편리, (pl.) 편의 시설",
        "bolded": "**facility**"
    },
    {
        "word": "circumstance",
        "meaning": "상황, 환경",
        "bolded": "**circumstance**"
    },
    {
        "word": "charity",
        "meaning": "자선, 자선 단체; 구호물자",
        "bolded": "**charity**"
    },
    {
        "word": "volunteer",
        "meaning": "자원봉사자, 지원자; 자발적으로 ~하다",
        "bolded": "**volunteer**"
    },
    {
        "word": "prospect",
        "meaning": "전망, 가능성",
        "bolded": "**prospect**"
    },
    {
        "word": "advantage",
        "meaning": "이익, 유리한 점",
        "bolded": "**advantage**"
    },
    {
        "word": "stereotype",
        "meaning": "고정 관념",
        "bolded": "**stereotype**"
    },
    {
        "word": "secure",
        "meaning": "안전한",
        "bolded": "**secure**"
    },
    {
        "word": "complex",
        "meaning": "복잡한; 복합 건물",
        "bolded": "**complex**"
    },
    {
        "word": "inadequate",
        "meaning": "부적당한, 불충분한",
        "bolded": "**inadequate**"
    },
    {
        "word": "proper",
        "meaning": "적절한, 알맞은",
        "bolded": "**proper**"
    },
    {
        "word": "indicate",
        "meaning": "나타내다, 가리키다",
        "bolded": "**indicate**"
    },
    {
        "word": "deserve",
        "meaning": "~할 자격이 있다, ~할 만하다",
        "bolded": "**deserve**"
    },
    {
        "word": "acquire",
        "meaning": "얻다, 습득하다",
        "bolded": "**acquire**"
    },
    {
        "word": "sign up for",
        "meaning": "(강좌 등에) 등록하다, ~을 신청[가입]하다",
        "bolded": "**sign up for**"
    },
    {
        "word": "contribute to",
        "meaning": "~의 한 원인이 되다; ~에 기여하다, 공헌하다",
        "bolded": "**contribute to**"
    },
    {
        "word": "put off",
        "meaning": "~을 연기하다[보류하다]",
        "bolded": "**put off**"
    }
]