[
    {
        "word": "garden",
        "meaning": "정원; 정원을 가꾸다",
        "bolded": "**garden**"
    },
    {
        "word": "apartment",
        "meaning": "아파트",
        "bolded": "**apartment**"
    },
    {
        "word": "yard",
        "meaning": "마당",
        "bolded": "**yard**"
    },
    {
        "word": "knock",
        "meaning": "노크를 하다, (문 등을) 두드리다",
        "bolded": "**knock**"
    },
    {
        "word": "soap",
        "meaning": "비누",
        "bolded": "**soap**"
    },
    {
        "word": "towel",
        "meaning": "타월, 수건",
        "bolded": "**towel**"
    },
    {
        "word": "curtain",
        "meaning": "커튼",
        "bolded": "**curtain**"
    },
    {
        "word": "mirror",
        "meaning": "거울",
        "bolded": "**mirror**"
    },
    {
        "word": "neighbor",
        "meaning": "이웃(사람)",
        "bolded": "**neighbor**"
    },
    {
        "word": "gate",
        "meaning": "문",
        "bolded": "**gate**"
    },
    {
        "word": "bedroom",
        "meaning": "침실",
        "bolded": "**bedroom**"
    },
    {
        "word": "roof",
        "meaning": "지붕",
        "bolded": "**roof**"
    },
    {
        "word": "garage",
        "meaning": "차고",
        "bolded": "**garage**"
    },
    {
        "word": "laundry",
        "meaning": "세탁물",
        "bolded": "**laundry**"
    },
    {
        "word": "water",
        "meaning": "물; 물을 주다",
        "bolded": "**water**"
    },
    {
        "word": "lawn",
        "meaning": "잔디",
        "bolded": "**lawn**"
    },
    {
        "word": "floor",
        "meaning": "마루, 바닥; 층",
        "bolded": "**floor**"
    },
    {
        "word": "feed",
        "meaning": "먹이를 주다",
        "bolded": "**feed**"
    },
    {
        "word": "bathroom",
        "meaning": "욕실",
        "bolded": "**bathroom**"
    },
    {
        "word": "ceiling",
        "meaning": "천장",
        "bolded": "**ceiling**"
    },
    {
        "word": "shelf",
        "meaning": "선반",
        "bolded": "**shelf**"
    },
    {
        "word": "drawer",
        "meaning": "서랍",
        "bolded": "**drawer**"
    },
    {
        "word": "lamp",
        "meaning": "전기스탠드, 램프",
        "bolded": "**lamp**"
    },
    {
        "word": "sheet",
        "meaning": "시트, 홑이불",
        "bolded": "**sheet**"
    },
    {
        "word": "stair",
        "meaning": "계단, 층계",
        "bolded": "**stair**"
    },
    {
        "word": "scale",
        "meaning": "체중계, 저울",
        "bolded": "**scale**"
    },
    {
        "word": "sink",
        "meaning": "싱크대, 개수대",
        "bolded": "**sink**"
    },
    {
        "word": "tap",
        "meaning": "수도꼭지",
        "bolded": "**tap**"
    },
    {
        "word": "turn on",
        "meaning": "(라디오, TV, 전기, 가스 등을) 켜다",
        "bolded": "**turn on**"
    },
    {
        "word": "in place",
        "meaning": "제자리에 (있는)",
        "bolded": "**in place**"
    }
]