[
    {
        "word": "play",
        "meaning": "놀다",
        "bolded": "**play**"
    },
    {
        "word": "walk",
        "meaning": "걷다; 산책시키다; 걷기",
        "bolded": "**walk**"
    },
    {
        "word": "run",
        "meaning": "달리다, 뛰다",
        "bolded": "**run**"
    },
    {
        "word": "kick",
        "meaning": "(발로) 차다",
        "bolded": "**kick**"
    },
    {
        "word": "jump",
        "meaning": "뛰다, 도약하다",
        "bolded": "**jump**"
    },
    {
        "word": "throw",
        "meaning": "던지다",
        "bolded": "**throw**"
    },
    {
        "word": "use",
        "meaning": "쓰다, 사용하다; 사용",
        "bolded": "**use**"
    },
    {
        "word": "close",
        "meaning": "닫다",
        "bolded": "**close**"
    },
    {
        "word": "cry",
        "meaning": "울다",
        "bolded": "**cry**"
    },
    {
        "word": "act",
        "meaning": "연기하다; 행동하다",
        "bolded": "**act**"
    },
    {
        "word": "move",
        "meaning": "움직이다; 이사하다",
        "bolded": "**move**"
    },
    {
        "word": "shout",
        "meaning": "소리[고함]치다",
        "bolded": "**shout**"
    },
    {
        "word": "carry",
        "meaning": "나르다; 가지고 다니다",
        "bolded": "**carry**"
    },
    {
        "word": "drop",
        "meaning": "떨어뜨리다",
        "bolded": "**drop**"
    },
    {
        "word": "try",
        "meaning": "노력하다, 애를 쓰다; 시도하다",
        "bolded": "**try**"
    },
    {
        "word": "check",
        "meaning": "확인하다, 점검하다",
        "bolded": "**check**"
    },
    {
        "word": "bring",
        "meaning": "가져오다, 데려오다",
        "bolded": "**bring**"
    },
    {
        "word": "laugh",
        "meaning": "(소리 내어) 웃다",
        "bolded": "**laugh**"
    },
    {
        "word": "have[take] a seat",
        "meaning": "자리에 앉다",
        "bolded": "**have[take] a seat**"
    },
    {
        "word": "get out of",
        "meaning": "~에서 나가[오]다; ~에서 내리다",
        "bolded": "**get out of**"
    }
]